{
    "controlPoints": [
        {
            "rotate": {
                "x": 0.0,
                "y": 0.0,
                "z": 0.0
            },
            "translate": {
                "x": 0.0537797175347805,
                "y": 1.0,
                "z": 6.707651138305664
            }
        },
        {
            "rotate": {
                "x": 0.0,
                "y": 0.27000001072883606,
                "z": 0.0
            },
            "translate": {
                "x": 0.6867884993553162,
                "y": 1.7624634504318237,
                "z": 13.093544960021973
            }
        },
        {
            "rotate": {
                "x": 0.0,
                "y": 0.5400000214576721,
                "z": 0.0
            },
            "translate": {
                "x": 2.62819766998291,
                "y": 2.602823257446289,
                "z": 19.990917205810547
            }
        },
        {
            "rotate": {
                "x": 0.0,
                "y": 0.8999999761581421,
                "z": 0.0
            },
            "translate": {
                "x": 7.094625473022461,
                "y": 4.1778974533081055,
                "z": 25.98166275024414
            }
        },
        {
            "rotate": {
                "x": 0.0,
                "y": 1.5199999809265137,
                "z": 0.0
            },
            "translate": {
                "x": 12.81912899017334,
                "y": 2.912125587463379,
                "z": 29.802902221679688
            }
        },
        {
            "rotate": {
                "x": 0.0,
                "y": 2.1600000858306885,
                "z": 0.0
            },
            "translate": {
                "x": 21.711671829223633,
                "y": 2.521958827972412,
                "z": 28.6069278717041
            }
        },
        {
            "rotate": {
                "x": 0.0,
                "y": 2.6700000762939453,
                "z": 0.0
            },
            "translate": {
                "x": 27.208341598510742,
                "y": 3.566237688064575,
                "z": 18.755735397338867
            }
        },
        {
            "rotate": {
                "x": 0.0,
                "y": 2.609999895095825,
                "z": 0.0
            },
            "translate": {
                "x": 28.72052574157715,
                "y": 5.790351390838623,
                "z": 11.60230827331543
            }
        }
    ]
}